lineinfile/__init__.py
lineinfile/__main__.py
lineinfile/py.typed
lineinfile-0.5.0.dist-info/METADATA
lineinfile-0.5.0.dist-info/WHEEL
lineinfile-0.5.0.dist-info/entry_points.txt
lineinfile-0.5.0.dist-info/licenses/LICENSE
lineinfile-0.5.0.dist-info/RECORD
