Metadata-Version: 2.4
Name: lineinfile
Version: 0.5.0
Summary: Add & remove lines in files by regex
Project-URL: Source Code, https://github.com/jwodder/lineinfile
Project-URL: Bug Tracker, https://github.com/jwodder/lineinfile/issues
Author-email: John Thorvald Wodder II <lineinfile@varonathe.org>
License-Expression: MIT
License-File: LICENSE
Keywords: add line,edit,ensure line,insert line,regexp,remove line,sed
Classifier: Environment :: Console
Classifier: Intended Audience :: Information Technology
Classifier: Intended Audience :: System Administrators
Classifier: Programming Language :: Python :: 3
Classifier: Programming Language :: Python :: 3 :: Only
Classifier: Programming Language :: Python :: 3.10
Classifier: Programming Language :: Python :: 3.11
Classifier: Programming Language :: Python :: 3.12
Classifier: Programming Language :: Python :: 3.13
Classifier: Programming Language :: Python :: 3.14
Classifier: Programming Language :: Python :: Implementation :: CPython
Classifier: Programming Language :: Python :: Implementation :: PyPy
Classifier: Topic :: Text Processing
Classifier: Typing :: Typed
Requires-Python: >=3.10
